dankmemer/__init__.py
dankmemer/client.py
dankmemer/exceptions.py
dankmemer/types.py
dankmemer/utils.py
dankmemer/routes/__init__.py
dankmemer/routes/all.py
dankmemer/routes/baits.py
dankmemer/routes/buckets.py
dankmemer/routes/creatures.py
dankmemer/routes/decorations.py
dankmemer/routes/events.py
dankmemer/routes/items.py
dankmemer/routes/locations.py
dankmemer/routes/npcs.py
dankmemer/routes/seasons.py
dankmemer/routes/skills.py
dankmemer/routes/skillsdata.py
dankmemer/routes/tanks.py
dankmemer/routes/tools.py
dankmemer_py-1.0.0rc1.dist-info/licenses/LICENSE
dankmemer_py-1.0.0rc1.dist-info/METADATA
dankmemer_py-1.0.0rc1.dist-info/WHEEL
dankmemer_py-1.0.0rc1.dist-info/top_level.txt
dankmemer_py-1.0.0rc1.dist-info/RECORD
