Metadata-Version: 2.4
Name: dankmemer.py
Version: 1.0.0rc1
Summary: A lightweight async wrapper for the DankAlert API.
Home-page: https://github.com/RayyanW786/dankmemer.py
Author: RayyanW786
License: MIT
Classifier: Programming Language :: Python :: 3
Classifier: Programming Language :: Python :: 3.7
Classifier: License :: OSI Approved :: MIT License
Classifier: Operating System :: OS Independent
Requires-Python: >=3.7
License-File: LICENSE
Requires-Dist: aiohttp>=3.7.4
Requires-Dist: rapidfuzz>=1.6.0
Provides-Extra: dev
Requires-Dist: pytest>=6.0; extra == "dev"
Requires-Dist: pytest-asyncio>=0.14.0; extra == "dev"
Dynamic: license-file
